syllables/__init__.py
syllables/py.typed
syllables-1.1.3.dist-info/METADATA
syllables-1.1.3.dist-info/WHEEL
syllables-1.1.3.dist-info/licenses/LICENSE
syllables-1.1.3.dist-info/RECORD
